{
  "frame": "frame2",
  "generatedBy": "build-cda-clone-workspace.mjs",
  "classIndex": 3207,
  "className": "mx.events.SWFBridgeRequest",
  "classNameNormalized": "mx.events.SWFBridgeRequest",
  "superName": "flash.events.Event",
  "superNameNormalized": "flash.events.Event",
  "domainBucket": "other",
  "flags": {
    "sealed": true,
    "final": false,
    "interface": false,
    "protectedNs": true
  },
  "interfaces": [],
  "iinitMethod": 50281,
  "cinitMethod": 50279,
  "iinitBytecode": {
    "codeLength": 22,
    "codeSha256": "b4afbc61ceade8488d7b5a3d520196da1f002e70704ef5fb6120ee4c3e5587ff",
    "bytecodeLineCount": 2
  },
  "cinitBytecode": {
    "codeLength": 279,
    "codeSha256": "80e83065e4ac0a41758dc911ebe85ad3eedacf01161b91ae36f6eb694ebf7511",
    "bytecodeLineCount": 18
  },
  "instanceMembers": [
    {
      "traitName": "clone",
      "traitKind": "method",
      "methodIndex": 50282,
      "methodName": "",
      "paramTypes": [],
      "returnType": "flash.events.Event",
      "hasBody": true,
      "codeLength": 30,
      "bytecode": {
        "codeLength": 30,
        "codeSha256": "c99f1177e201ab386a3e2d49cc8b2ab6c4a84a1e4514ea7a8cb163c2c8042d09",
        "bytecodeLineCount": 2
      }
    }
  ],
  "staticMembers": [
    {
      "traitName": "marshal",
      "traitKind": "method",
      "methodIndex": 50280,
      "methodName": "",
      "paramTypes": [
        "flash.events.Event"
      ],
      "returnType": "mx.events.SWFBridgeRequest",
      "hasBody": true,
      "codeLength": 35,
      "bytecode": {
        "codeLength": 35,
        "codeSha256": "235875eda957340ba07724d4fb24f7b704594b26868468b9d8c7a08f6f2ac2d4",
        "bytecodeLineCount": 3
      }
    }
  ]
}
