{
  "frame": "frame2",
  "generatedBy": "build-cda-clone-workspace.mjs",
  "classIndex": 3845,
  "className": "com.hurlant.util.ArrayUtil",
  "classNameNormalized": "com.hurlant.util.ArrayUtil",
  "superName": "Object",
  "superNameNormalized": "Object",
  "domainBucket": "other",
  "flags": {
    "sealed": true,
    "final": false,
    "interface": false,
    "protectedNs": true
  },
  "interfaces": [],
  "iinitMethod": 56601,
  "cinitMethod": 56599,
  "iinitBytecode": {
    "codeLength": 6,
    "codeSha256": "8ff32749a852a1d83829c6a3fac8ec00822f06b5c7177f9ebb43a09287b2101a",
    "bytecodeLineCount": 1
  },
  "cinitBytecode": {
    "codeLength": 3,
    "codeSha256": "a968960b201420953c59656517f78c74a88e3e2aebf37839d8e70f6e531134c4",
    "bytecodeLineCount": 1
  },
  "instanceMembers": [],
  "staticMembers": [
    {
      "traitName": "equals",
      "traitKind": "method",
      "methodIndex": 56600,
      "methodName": "",
      "paramTypes": [
        "flash.utils.ByteArray",
        "flash.utils.ByteArray"
      ],
      "returnType": "Boolean",
      "hasBody": true,
      "codeLength": 62,
      "bytecode": {
        "codeLength": 62,
        "codeSha256": "111300d233b345775069a0ea47ab96ff5acbf26d01e094c8ad5583d3981977ae",
        "bytecodeLineCount": 4
      }
    }
  ]
}
