{
  "frame": "frame2",
  "generatedBy": "build-cda-clone-workspace.mjs",
  "classIndex": 170,
  "className": "mx.binding.IWatcherSetupUtil2",
  "classNameNormalized": "mx.binding.IWatcherSetupUtil2",
  "superName": "*",
  "superNameNormalized": "",
  "domainBucket": "other",
  "flags": {
    "sealed": true,
    "final": false,
    "interface": true,
    "protectedNs": false
  },
  "interfaces": [],
  "iinitMethod": 3577,
  "cinitMethod": 3575,
  "iinitBytecode": null,
  "cinitBytecode": {
    "codeLength": 1,
    "codeSha256": "333e0a1e27815d0ceee55c473fe3dc93d56c63e3bee2b3b4aee8eed6d70191a3",
    "bytecodeLineCount": 1
  },
  "instanceMembers": [
    {
      "traitName": "mx.binding:IWatcherSetupUtil2.setup",
      "traitKind": "method",
      "methodIndex": 3576,
      "methodName": "",
      "paramTypes": [
        "Object",
        "Function",
        "Function",
        "Array",
        "Array"
      ],
      "returnType": "void",
      "hasBody": false,
      "codeLength": 0,
      "bytecode": null
    }
  ],
  "staticMembers": []
}
