{
  "frame": "frame2",
  "generatedBy": "build-cda-clone-workspace.mjs",
  "classIndex": 2753,
  "className": "spark.components.supportClasses.InteractionState",
  "classNameNormalized": "spark.components.supportClasses.InteractionState",
  "superName": "Object",
  "superNameNormalized": "Object",
  "domainBucket": "other",
  "flags": {
    "sealed": true,
    "final": true,
    "interface": false,
    "protectedNs": true
  },
  "interfaces": [],
  "iinitMethod": 46334,
  "cinitMethod": 46333,
  "iinitBytecode": {
    "codeLength": 6,
    "codeSha256": "8ff32749a852a1d83829c6a3fac8ec00822f06b5c7177f9ebb43a09287b2101a",
    "bytecodeLineCount": 1
  },
  "cinitBytecode": {
    "codeLength": 37,
    "codeSha256": "dfaaf0f6edb4ce99dca0fea50b680bb15f6e6be88b8a99c7fbe2bb9fdcfd4302",
    "bytecodeLineCount": 3
  },
  "instanceMembers": [],
  "staticMembers": []
}
