{
  "frame": "frame2",
  "generatedBy": "build-cda-clone-workspace.mjs",
  "classIndex": 3894,
  "className": "PrivateNs.ObserveMethodProcessor",
  "classNameNormalized": "PrivateNs.ObserveMethodProcessor",
  "superName": "Object",
  "superNameNormalized": "Object",
  "domainBucket": "other",
  "flags": {
    "sealed": true,
    "final": false,
    "interface": false,
    "protectedNs": true
  },
  "interfaces": [
    "org.spicefactory.parsley.core.registry.ObjectProcessor"
  ],
  "iinitMethod": 56935,
  "cinitMethod": 56934,
  "iinitBytecode": {
    "codeLength": 38,
    "codeSha256": "d23d880c33c7fb60aac7a31fd52cec2533c98dc76cbfa6a05c953673536116f8",
    "bytecodeLineCount": 3
  },
  "cinitBytecode": {
    "codeLength": 3,
    "codeSha256": "a968960b201420953c59656517f78c74a88e3e2aebf37839d8e70f6e531134c4",
    "bytecodeLineCount": 1
  },
  "instanceMembers": [
    {
      "traitName": "addObserver",
      "traitKind": "method",
      "methodIndex": 56938,
      "methodName": "",
      "paramTypes": [],
      "returnType": "void",
      "hasBody": true,
      "codeLength": 56,
      "bytecode": {
        "codeLength": 56,
        "codeSha256": "a2ede6f8407d2186b53ab18e86984d68d978d85d7cacb4426ff20c064501e8dc",
        "bytecodeLineCount": 4
      }
    },
    {
      "traitName": "postDestroy",
      "traitKind": "method",
      "methodIndex": 56937,
      "methodName": "",
      "paramTypes": [],
      "returnType": "void",
      "hasBody": true,
      "codeLength": 18,
      "bytecode": {
        "codeLength": 18,
        "codeSha256": "aaa028e7178e000ac87352a3db02c5dca1c230a5056c27d670884f88dfbe3dcf",
        "bytecodeLineCount": 2
      }
    },
    {
      "traitName": "preInit",
      "traitKind": "method",
      "methodIndex": 56936,
      "methodName": "",
      "paramTypes": [],
      "returnType": "void",
      "hasBody": true,
      "codeLength": 18,
      "bytecode": {
        "codeLength": 18,
        "codeSha256": "b26818aecde79c28c476e799cc8fb942b138d91b9f9c813e24275fb1bbaf56ae",
        "bytecodeLineCount": 2
      }
    },
    {
      "traitName": "removeObserver",
      "traitKind": "method",
      "methodIndex": 56939,
      "methodName": "",
      "paramTypes": [],
      "returnType": "void",
      "hasBody": true,
      "codeLength": 22,
      "bytecode": {
        "codeLength": 22,
        "codeSha256": "7615e8463d758cee3f2dbd82793bbec711ff1e398deaaca6d0bb54456b8679a9",
        "bytecodeLineCount": 2
      }
    },
    {
      "traitName": "toString",
      "traitKind": "method",
      "methodIndex": 56940,
      "methodName": "",
      "paramTypes": [],
      "returnType": "String",
      "hasBody": true,
      "codeLength": 18,
      "bytecode": {
        "codeLength": 18,
        "codeSha256": "6df58ba4b5e7f93785abb5464002bbb3794466a31f5eb9e73a215fa1dff03bc2",
        "bytecodeLineCount": 2
      }
    }
  ],
  "staticMembers": []
}
