{
  "frame": "frame2",
  "generatedBy": "build-cda-clone-workspace.mjs",
  "classIndex": 1831,
  "className": "flashx.textLayout.formats.VerticalAlign",
  "classNameNormalized": "flashx.textLayout.formats.VerticalAlign",
  "superName": "Object",
  "superNameNormalized": "Object",
  "domainBucket": "flash",
  "flags": {
    "sealed": true,
    "final": true,
    "interface": false,
    "protectedNs": true
  },
  "interfaces": [],
  "iinitMethod": 34934,
  "cinitMethod": 34933,
  "iinitBytecode": {
    "codeLength": 6,
    "codeSha256": "8ff32749a852a1d83829c6a3fac8ec00822f06b5c7177f9ebb43a09287b2101a",
    "bytecodeLineCount": 1
  },
  "cinitBytecode": {
    "codeLength": 48,
    "codeSha256": "f83f51dc3e49e37b7ac548e8538e34fcce7f2e70aa98e865ae10f0a5a1366cb9",
    "bytecodeLineCount": 3
  },
  "instanceMembers": [],
  "staticMembers": []
}
