{
  "frame": "frame2",
  "generatedBy": "build-cda-clone-workspace.mjs",
  "classIndex": 236,
  "className": "org.spicefactory.parsley.flex.tag.builder.FlexConfigTag",
  "classNameNormalized": "org.spicefactory.parsley.flex.tag.builder.FlexConfigTag",
  "superName": "Object",
  "superNameNormalized": "Object",
  "domainBucket": "other",
  "flags": {
    "sealed": true,
    "final": false,
    "interface": false,
    "protectedNs": true
  },
  "interfaces": [
    "org.spicefactory.parsley.flex.tag.builder.BootstrapConfigProcessor"
  ],
  "iinitMethod": 5620,
  "cinitMethod": 5618,
  "iinitBytecode": {
    "codeLength": 6,
    "codeSha256": "8ff32749a852a1d83829c6a3fac8ec00822f06b5c7177f9ebb43a09287b2101a",
    "bytecodeLineCount": 1
  },
  "cinitBytecode": {
    "codeLength": 3,
    "codeSha256": "a968960b201420953c59656517f78c74a88e3e2aebf37839d8e70f6e531134c4",
    "bytecodeLineCount": 1
  },
  "instanceMembers": [
    {
      "traitName": "processConfig",
      "traitKind": "method",
      "methodIndex": 5619,
      "methodName": "",
      "paramTypes": [
        "org.spicefactory.parsley.core.bootstrap.BootstrapConfig"
      ],
      "returnType": "void",
      "hasBody": true,
      "codeLength": 23,
      "bytecode": {
        "codeLength": 23,
        "codeSha256": "a3fbc8ef9f6b322339b1e3ee1b5dcbadbf70c87d57d2a89d833416e713f26042",
        "bytecodeLineCount": 2
      }
    }
  ],
  "staticMembers": []
}
